{"cameraMode":{"drawMode":0,"name":"Shaded","section":"Shading Mode"},"sceneLighting":true,"audioPlay":false,"sceneViewState":{"m_AlwaysRefresh":false,"showFog":true,"showSkybox":true,"showFlares":true,"showImageEffects":true,"showParticleSystems":true,"showVisualEffectGraphs":true,"m_FxEnabled":true},"in2DMode":false,"pivot":{"x":11.272525787353516,"y":0.034877706319093707,"z":35.61410140991211},"rotation":{"x":0.09850060939788819,"y":0.9013773798942566,"z":-0.2901257276535034,"w":0.3060234487056732},"size":1.011804223060608,"orthographic":false}